gradio_image_annotator/__init__.py
gradio_image_annotator/image_annotator.py
gradio_image_annotator/image_annotator.pyi
gradio_image_annotator/templates/component/__vite-browser-external-2447137e.js
gradio_image_annotator/templates/component/index.js
gradio_image_annotator/templates/component/style.css
gradio_image_annotator/templates/component/wrapper-6f348d45-f837cf34.js
gradio_image_annotator/templates/example/index.js
gradio_image_annotator/templates/example/style.css
gradio_image_annotator-0.0.1.dist-info/METADATA
gradio_image_annotator-0.0.1.dist-info/WHEEL
gradio_image_annotator-0.0.1.dist-info/RECORD
